lambda_labs_wrapper/src/__init__.py
lambda_labs_wrapper/test/__init__.py
lambda_labs_wrapper-0.0.1.dist-info/METADATA
lambda_labs_wrapper-0.0.1.dist-info/WHEEL
lambda_labs_wrapper-0.0.1.dist-info/top_level.txt
lambda_labs_wrapper-0.0.1.dist-info/RECORD
