Metadata-Version: 2.1
Name: lambda-labs-wrapper
Version: 0.0.1
Summary: A python wrapper for the lambda labs API.
Author-email: Liam Earley <liamearley7@gmail.com>
Project-URL: Homepage, https://github.com/Liam-E2/lambda_labs_wrapper
Classifier: Programming Language :: Python :: 3
Classifier: License :: OSI Approved :: MIT License
Classifier: Operating System :: OS Independent
Requires-Python: >=3.7
